fast_astropy_timeseries_binning-0.0.2.dist-info/RECORD
fast_astropy_timeseries_binning-0.0.2.dist-info/LICENSE
fast_astropy_timeseries_binning-0.0.2.dist-info/WHEEL
fast_astropy_timeseries_binning-0.0.2.dist-info/top_level.txt
fast_astropy_timeseries_binning-0.0.2.dist-info/METADATA
fast_astropy_timeseries_binning/version.py
fast_astropy_timeseries_binning/__init__.py
fast_astropy_timeseries_binning/reducer.py
fast_astropy_timeseries_binning/_fast_astropy_timeseries_binning.cpython-310-darwin.so
